asynciomagic.py
asyncio_ipython_magic-0.0.3.dist-info/DESCRIPTION.rst
asyncio_ipython_magic-0.0.3.dist-info/METADATA
asyncio_ipython_magic-0.0.3.dist-info/RECORD
asyncio_ipython_magic-0.0.3.dist-info/WHEEL
asyncio_ipython_magic-0.0.3.dist-info/metadata.json
asyncio_ipython_magic-0.0.3.dist-info/top_level.txt
