Metadata-Version: 2.0
Name: asyncio-ipython-magic
Version: 0.0.3
Summary: An extension for IPython that help to run AsyncIO code in your interactive session.
Home-page: https://github.com/Gr1N/asyncio-ipython-magic
Author: Nikita Grishko
Author-email: gr1n@protonmain.com
License: UNKNOWN
Platform: UNKNOWN
Classifier: Development Status :: 3 - Alpha
Classifier: Framework :: IPython
Classifier: Intended Audience :: Developers
Classifier: Operating System :: OS Independent
Classifier: Programming Language :: Python
Classifier: Programming Language :: Python :: 3
Classifier: Programming Language :: Python :: 3.5
Classifier: Programming Language :: Python :: 3.6
Classifier: Topic :: Software Development :: Libraries :: Python Modules
Requires-Dist: ipython
